nlp_toolkit_services_py_client/__init__.py
nlp_toolkit_services_py_client/dependency_pb2.py
nlp_toolkit_services_py_client/dependency_pb2.pyi
nlp_toolkit_services_py_client/dependency_pb2_grpc.py
nlp_toolkit_services_py_client/ner_pb2.py
nlp_toolkit_services_py_client/ner_pb2.pyi
nlp_toolkit_services_py_client/ner_pb2_grpc.py
nlp_toolkit_services_py_client/word_segment_pb2.py
nlp_toolkit_services_py_client/word_segment_pb2.pyi
nlp_toolkit_services_py_client/word_segment_pb2_grpc.py
word_segment_grpc_client-0.1.7.dist-info/METADATA
word_segment_grpc_client-0.1.7.dist-info/WHEEL
word_segment_grpc_client-0.1.7.dist-info/top_level.txt
word_segment_grpc_client-0.1.7.dist-info/RECORD
