Metadata-Version: 2.4
Name: word-segment-grpc-client
Version: 0.1.7
Summary: Python gRPC client stubs for the word-segment service.
Project-URL: Homepage, https://github.com/citadel2024/nlp-toolkit-services
Project-URL: Repository, https://github.com/citadel2024/nlp-toolkit-services
Requires-Python: >=3.9
Requires-Dist: grpcio>=1.68.1
Requires-Dist: protobuf>=5
